_das2.cp310-win_amd64.pyd
das2/__init__.py
das2/auth.py
das2/cdf.py
das2/cli.py
das2/container.py
das2/dastime.py
das2/dataset.py
das2/mpl.py
das2/node.py
das2/pkt.py
das2/reader.py
das2/source.py
das2/streamsrc.py
das2/toml.py
das2/util.py
das2/verify.py
das2/pycdf/__init__.py
das2/pycdf/const.py
das2/xsd/das-basic-doc-ns-v3.0.xsd
das2/xsd/das-basic-stream-ns-v3.0.xsd
das2/xsd/das-basic-stream-v2.2.xsd
das2/xsd/das-basic-stream-v3.0.xsd
das2py-2.3.1.data/scripts/das_verify
das2py-2.3.1.dist-info/LICENSE
das2py-2.3.1.dist-info/METADATA
das2py-2.3.1.dist-info/WHEEL
das2py-2.3.1.dist-info/entry_points.txt
das2py-2.3.1.dist-info/top_level.txt
das2py-2.3.1.dist-info/RECORD
