Metadata-Version: 2.1
Name: das2py
Version: 2.3.1
Summary: An efficient space physics data client for python
Home-page: https://das2.org/das2py
Author: C Piker
Author-email: C Piker <cpiker@users.noreply.github.com>
Maintainer-email: K Steele <KaiwenS7@users.noreply.github.com>
License: MIT License
Project-URL: Homepage, https://das2.org/das2py
Project-URL: Repository, https://github.com/das-developers/das2py
Keywords: space-physics,magneosphere,das2
Requires-Python: >=2.7
License-File: LICENSE
Requires-Dist: numpy
Requires-Dist: lxml
